deforum_flux/__init__.py
deforum_flux-0.1.2.dist-info/licenses/LICENSE
flux/__init__.py
flux/__main__.py
flux/cli.py
flux/cli_control.py
flux/cli_fill.py
flux/cli_kontext.py
flux/cli_redux.py
flux/content_filters.py
flux/math.py
flux/model.py
flux/sampling.py
flux/util.py
flux/modules/autoencoder.py
flux/modules/conditioner.py
flux/modules/image_embedders.py
flux/modules/layers.py
flux/modules/lora.py
flux/trt/__init__.py
flux/trt/trt_manager.py
flux/trt/engine/__init__.py
flux/trt/engine/base_engine.py
flux/trt/engine/clip_engine.py
flux/trt/engine/t5_engine.py
flux/trt/engine/transformer_engine.py
flux/trt/engine/vae_engine.py
flux/trt/trt_config/__init__.py
flux/trt/trt_config/base_trt_config.py
flux/trt/trt_config/clip_trt_config.py
flux/trt/trt_config/t5_trt_config.py
flux/trt/trt_config/transformer_trt_config.py
flux/trt/trt_config/vae_trt_config.py
deforum_flux-0.1.2.dist-info/METADATA
deforum_flux-0.1.2.dist-info/WHEEL
deforum_flux-0.1.2.dist-info/top_level.txt
deforum_flux-0.1.2.dist-info/RECORD
