Metadata-Version: 2.4
Name: deforum-flux
Version: 0.1.2
Summary: Flux backend for Deforum
Author-email: Deforum Inc <hello@deforum.io>
License: MIT
Project-URL: Homepage, https://github.com/deforum/flux
Project-URL: Repository, https://github.com/deforum/flux
Requires-Python: >=3.12
License-File: LICENSE
Dynamic: license-file
